cli_tarot/LICENSE.md
cli_tarot/README.md
cli_tarot/__init__.py
cli_tarot/__main__.py
cli_tarot/ascii_art.py
cli_tarot/card_directory.py
cli_tarot/card_meanings.py
cli_tarot/constants.py
cli_tarot/output.py
cli_tarot/readings.py
cli_tarot-1.0.4.dist-info/entry_points.txt
cli_tarot-1.0.4.dist-info/WHEEL
cli_tarot-1.0.4.dist-info/METADATA
cli_tarot-1.0.4.dist-info/RECORD
