Metadata-Version: 2.1
Name: cli-tarot
Version: 1.0.4
Summary: A convenient way to get a tarot reading on your terminal!
Keywords: tarot,command line,cli
Requires-Python: >=3.9
